LICENSE.md
textual_terminal/__init__.py
textual_terminal/_terminal.py
textual_terminal-0.3.0.dist-info/WHEEL
textual_terminal-0.3.0.dist-info/LICENSE.md
textual_terminal-0.3.0.dist-info/METADATA
textual_terminal-0.3.0.dist-info/RECORD
