Metadata-Version: 2.1
Name: textual-terminal
Version: 0.3.0
Summary: A terminal emulator widget for Textual.
Home-page: https://github.com/mitosch/textual-terminal
License: LGPL-3.0-or-later
Keywords: textual,textual terminal,textual terminal emulator,textual subprocess
Author: Mischa Schindowski
Author-email: mschindowski@gmail.com
Requires-Python: >=3.7,<4.0
Classifier: Development Status :: 4 - Beta
Classifier: Environment :: Console
Classifier: Intended Audience :: Developers
Classifier: License :: OSI Approved :: GNU Lesser General Public License v3 or later (LGPLv3+)
Classifier: Operating System :: MacOS
Classifier: Operating System :: Microsoft :: Windows :: Windows 10
Classifier: Operating System :: Microsoft :: Windows :: Windows 11
Classifier: Operating System :: POSIX :: Linux
Classifier: Programming Language :: Python :: 3
Classifier: Programming Language :: Python :: 3.7
Classifier: Programming Language :: Python :: 3.8
Classifier: Programming Language :: Python :: 3.9
Classifier: Programming Language :: Python :: 3.10
Classifier: Programming Language :: Python :: 3.11
Requires-Dist: pyte (>=0.8.1,<0.9.0)
Requires-Dist: textual (>=0.8.0)
Project-URL: Repository, https://github.com/mitosch/textual-terminal
